MANIFEST.in
setup.py
randommac/OUI.list
randommac/__init__.py
randommac/execute_bash_command.py
randommac/extract_information_from_nmcli.py
randommac/generate_random_MAC.py
randommac/help.py
randommac/randommac_commandline.py
randommac/randommac_interface.py
randommac/spoof_MAC_address.py
randommac.egg-info/PKG-INFO
randommac.egg-info/SOURCES.txt
randommac.egg-info/dependency_links.txt
randommac.egg-info/entry_points.txt
randommac.egg-info/top_level.txt